{
  "project_info": {
    "project_number": "1086287773639",
    "firebase_url": "https://smartvote-eec04.firebaseio.com",
    "project_id": "smartvote-eec04",
    "storage_bucket": "smartvote-eec04.appspot.com"
  },
  "client": [
    {
      "client_info": {
        "mobilesdk_app_id": "1:1086287773639:android:57cadff87bc3ecab0623e2",
        "android_client_info": {
          "package_name": "com.example.smartvote"
        }
      },
      "oauth_client": [
        {
          "client_id": "1086287773639-f1av94diuc5vshtrocqs4o0l74npfp83.apps.googleusercontent.com",
          "client_type": 1,
          "android_info": {
            "package_name": "com.example.smartvote",
            "certificate_hash": "1b1fc9d994721ba1d165e19f0509908cfc8110b1"
          }
        },
        {
          "client_id": "1086287773639-6699vb5ue2tfl6n0evpel6lt7q3qqico.apps.googleusercontent.com",
          "client_type": 3
        }
      ],
      "api_key": [
        {
          "current_key": "AIzaSyCHmxJoO55p2Top6fxXZevKnxYNdO5ocUU"
        }
      ],
      "services": {
        "appinvite_service": {
          "other_platform_oauth_client": [
            {
              "client_id": "1086287773639-6699vb5ue2tfl6n0evpel6lt7q3qqico.apps.googleusercontent.com",
              "client_type": 3
            }
          ]
        }
      }
    }
  ],
  "configuration_version": "1"
}